{
  "tables": [
    {
      "id": "aLe-2QywIxjXoM77qsWLM",
      "name": "MovimentacaoMaterial",
      "x": 343.0789544261693,
      "y": -291.5864755370763,
      "locked": false,
      "fields": [
        {
          "name": "Id",
          "type": "INTEGER",
          "default": "",
          "check": "",
          "primary": true,
          "unique": true,
          "notNull": true,
          "increment": true,
          "comment": "",
          "id": "S-snYCLpgdntU98e8V5Pc"
        },
        {
          "id": "gVBC-pSXzhT65M-HmrHpa",
          "name": "IdUsuarioSolicitante",
          "type": "TINYINT",
          "default": "",
          "check": "",
          "primary": false,
          "unique": false,
          "notNull": true,
          "increment": false,
          "comment": "",
          "size": "",
          "values": []
        },
        {
          "id": "Yg1WQ67JEJvKA4j1dFkJH",
          "name": "IdTipoMovimentacao",
          "type": "TINYINT",
          "default": "",
          "check": "",
          "primary": false,
          "unique": false,
          "notNull": true,
          "increment": false,
          "comment": "",
          "size": "",
          "values": []
        },
        {
          "id": "IctnJuTacfy3FDG3Hemt_",
          "name": "IdColaboradorOrigem",
          "type": "SMALLINT",
          "default": "",
          "check": "",
          "primary": false,
          "unique": false,
          "notNull": false,
          "increment": false,
          "comment": "",
          "size": "",
          "values": []
        },
        {
          "id": "pMPR5N5KOpCy1a_dMaTJx",
          "name": "IdMaterial",
          "type": "SMALLINT",
          "default": "",
          "check": "",
          "primary": false,
          "unique": false,
          "notNull": true,
          "increment": false,
          "comment": "",
          "size": "",
          "values": []
        },
        {
          "id": "TQ2ILMkD6ITHwxrgknVP_",
          "name": "DataMovimentacao",
          "type": "DATETIME",
          "default": "",
          "check": "",
          "primary": false,
          "unique": false,
          "notNull": true,
          "increment": false,
          "comment": "",
          "size": "",
          "values": []
        },
        {
          "id": "xT1jxPlTL5PB2qFEJEJr3",
          "name": "Justificativa",
          "type": "VARCHAR",
          "default": "",
          "check": "",
          "primary": false,
          "unique": false,
          "notNull": true,
          "increment": false,
          "comment": "",
          "size": 500
        },
        {
          "id": "kcO2xzLQ0kKD9MTesuwki",
          "name": "Quantidade",
          "type": "SMALLINT",
          "default": "",
          "check": "",
          "primary": false,
          "unique": false,
          "notNull": true,
          "increment": false,
          "comment": "",
          "size": "",
          "values": []
        },
        {
          "id": "oeKG-HcgXFaaM-tdZgvpa",
          "name": "IdUsuarioUltimaAtualizacao",
          "type": "TINYINT",
          "default": "",
          "check": "",
          "primary": false,
          "unique": false,
          "notNull": false,
          "increment": false,
          "comment": "",
          "size": "",
          "values": []
        },
        {
          "id": "IIuu5l8w3RDQ9yeG15Zdv",
          "name": "DataUltimaAtualizacao",
          "type": "DATETIME",
          "default": "",
          "check": "",
          "primary": false,
          "unique": false,
          "notNull": false,
          "increment": false,
          "comment": "",
          "size": "",
          "values": []
        }
      ],
      "comment": "",
      "indices": [],
      "color": "#175e7a"
    },
    {
      "id": "EgUBOf4V3YIqSYCglNDwm",
      "name": "Usuario",
      "x": -783.3134141363106,
      "y": -1105.2336024629637,
      "locked": false,
      "fields": [
        {
          "name": "Id",
          "type": "TINYINT",
          "default": "",
          "check": "",
          "primary": true,
          "unique": true,
          "notNull": true,
          "increment": true,
          "comment": "",
          "id": "oTb24hApjtLd3cIZlBWuG",
          "size": "",
          "values": []
        },
        {
          "id": "SkTcU36OY30dsgm3OID2W",
          "name": "IdPerfilAcesso",
          "type": "TINYINT",
          "default": "",
          "check": "",
          "primary": false,
          "unique": false,
          "notNull": true,
          "increment": false,
          "comment": "",
          "size": "",
          "values": []
        },
        {
          "id": "ypdfz29D59TuZIi7HkyUZ",
          "name": "IdStatusUsuario",
          "type": "TINYINT",
          "default": "",
          "check": "",
          "primary": false,
          "unique": false,
          "notNull": true,
          "increment": false,
          "comment": "",
          "size": "",
          "values": []
        },
        {
          "id": "irjexJJreLK45xYmDE3YH",
          "name": "Nome",
          "type": "VARCHAR",
          "default": "",
          "check": "",
          "primary": false,
          "unique": false,
          "notNull": true,
          "increment": false,
          "comment": "",
          "size": 100
        },
        {
          "id": "CJSZGw12ZfSgUVmLmmi-Y",
          "name": "Email",
          "type": "VARCHAR",
          "default": "",
          "check": "",
          "primary": false,
          "unique": false,
          "notNull": true,
          "increment": false,
          "comment": "",
          "size": 160
        },
        {
          "id": "i_F1Z-JFznAlc_oBFFfJA",
          "name": "Senha",
          "type": "VARCHAR",
          "default": "",
          "check": "",
          "primary": false,
          "unique": false,
          "notNull": true,
          "increment": false,
          "comment": "",
          "size": 40
        },
        {
          "id": "VkAw7lEJ_b9YNdCRMwwfS",
          "name": "IdUsuarioUltimaAtualizacao",
          "type": "TINYINT",
          "default": "",
          "check": "",
          "primary": false,
          "unique": false,
          "notNull": false,
          "increment": false,
          "comment": "",
          "size": "",
          "values": []
        },
        {
          "id": "QVcWsneL3Fc4P9JP4x_q_",
          "name": "DataUltimaAtualizacao",
          "type": "DATETIME",
          "default": "",
          "check": "",
          "primary": false,
          "unique": false,
          "notNull": false,
          "increment": false,
          "comment": "",
          "size": "",
          "values": []
        }
      ],
      "comment": "",
      "indices": [],
      "color": "#175e7a"
    },
    {
      "id": "znT_6XPvYhsgtcjSti49b",
      "name": "CategoriaAtivo",
      "x": -2836.0653218801153,
      "y": 1126.7252091161617,
      "locked": false,
      "fields": [
        {
          "name": "Id",
          "type": "TINYINT",
          "default": "",
          "check": "",
          "primary": true,
          "unique": true,
          "notNull": true,
          "increment": true,
          "comment": "",
          "id": "-ds9J9h4tE4R1HXNEE9lL",
          "size": "",
          "values": []
        },
        {
          "id": "M3jjxWEH4jusmyWxMS1hq",
          "name": "Nome",
          "type": "VARCHAR",
          "default": "",
          "check": "",
          "primary": false,
          "unique": false,
          "notNull": true,
          "increment": false,
          "comment": "",
          "size": 15
        }
      ],
      "comment": "",
      "indices": [],
      "color": "#175e7a"
    },
    {
      "id": "aMedcj3vxJ6c6Txe6vQ2h",
      "name": "Colaborador",
      "x": -1940.060962255921,
      "y": -38.91891724977182,
      "locked": false,
      "fields": [
        {
          "name": "Id",
          "type": "SMALLINT",
          "default": "",
          "check": "",
          "primary": true,
          "unique": true,
          "notNull": true,
          "increment": true,
          "comment": "",
          "id": "2M58dRGLJvoEwgvr-PLJL",
          "size": "",
          "values": []
        },
        {
          "id": "e3J5JtnhTirfMvNoFVxV-",
          "name": "IdDepartamento",
          "type": "TINYINT",
          "default": "",
          "check": "",
          "primary": false,
          "unique": false,
          "notNull": true,
          "increment": false,
          "comment": "",
          "size": "",
          "values": []
        },
        {
          "id": "jgGtoUBpNDX6t6tSVhBBP",
          "name": "IdCargo",
          "type": "TINYINT",
          "default": "",
          "check": "",
          "primary": false,
          "unique": false,
          "notNull": true,
          "increment": false,
          "comment": "",
          "size": "",
          "values": []
        },
        {
          "id": "zdw1qx4GesWHtx-Ygrhm9",
          "name": "IdFilial",
          "type": "TINYINT",
          "default": "",
          "check": "",
          "primary": false,
          "unique": false,
          "notNull": true,
          "increment": false,
          "comment": "",
          "size": "",
          "values": []
        },
        {
          "id": "MezSKC28YcksaNx9TLbwc",
          "name": "Nome",
          "type": "VARCHAR",
          "default": "",
          "check": "",
          "primary": false,
          "unique": false,
          "notNull": true,
          "increment": false,
          "comment": "",
          "size": 100
        },
        {
          "id": "ZnImAwbqS8pJrDBYznhCN",
          "name": "Cpf",
          "type": "CHAR",
          "default": "",
          "check": "",
          "primary": false,
          "unique": true,
          "notNull": true,
          "increment": false,
          "comment": "",
          "size": 11
        },
        {
          "id": "jVbRsmvUHZdyc6X1EtS9W",
          "name": "IdUsuarioUltimaAtualizacao",
          "type": "TINYINT",
          "default": "",
          "check": "",
          "primary": false,
          "unique": false,
          "notNull": false,
          "increment": false,
          "comment": "",
          "size": "",
          "values": []
        },
        {
          "id": "y7X2aU28_6tYytCTKjhCf",
          "name": "DataUltimaAtualizacao",
          "type": "DATETIME",
          "default": "",
          "check": "",
          "primary": false,
          "unique": false,
          "notNull": false,
          "increment": false,
          "comment": "",
          "size": "",
          "values": []
        }
      ],
      "comment": "",
      "indices": [],
      "color": "#175e7a"
    },
    {
      "id": "l-UUUMGmE5jh0crDWddKS",
      "name": "Filial",
      "x": -2860.2930795139227,
      "y": 114.12960336767341,
      "locked": false,
      "fields": [
        {
          "name": "Id",
          "type": "TINYINT",
          "default": "",
          "check": "",
          "primary": true,
          "unique": true,
          "notNull": true,
          "increment": true,
          "comment": "",
          "id": "HdHStf7sU7DSR2zhTqmKV",
          "size": "",
          "values": []
        },
        {
          "id": "2aFBABHWYVIfwzpZ7MwxQ",
          "name": "Nome",
          "type": "VARCHAR",
          "default": "",
          "check": "",
          "primary": false,
          "unique": false,
          "notNull": true,
          "increment": false,
          "comment": "",
          "size": 50
        }
      ],
      "comment": "",
      "indices": [],
      "color": "#175e7a"
    },
    {
      "id": "Y453M_v1rTjDrkxgymu9e",
      "name": "Departamento",
      "x": -2906.1384836024513,
      "y": -364.5722271318748,
      "locked": false,
      "fields": [
        {
          "name": "Id",
          "type": "TINYINT",
          "default": "",
          "check": "",
          "primary": true,
          "unique": true,
          "notNull": true,
          "increment": true,
          "comment": "",
          "id": "hYKj0byaYCzCvgYaRDARP",
          "size": "",
          "values": []
        },
        {
          "id": "9oyD4sJLeq68-fHxZ9N8p",
          "name": "Nome",
          "type": "VARCHAR",
          "default": "",
          "check": "",
          "primary": false,
          "unique": false,
          "notNull": true,
          "increment": false,
          "comment": "",
          "size": 60
        }
      ],
      "comment": "",
      "indices": [],
      "color": "#175e7a"
    },
    {
      "id": "Bq7tOrufYBTd8Bgx2MM3E",
      "name": "Cargo",
      "x": -3108.394028997954,
      "y": -92.98095679149174,
      "locked": false,
      "fields": [
        {
          "name": "Id",
          "type": "TINYINT",
          "default": "",
          "check": "",
          "primary": true,
          "unique": true,
          "notNull": true,
          "increment": true,
          "comment": "",
          "id": "xF8K_mMqHlH3wOsJpk35v",
          "size": "",
          "values": []
        },
        {
          "id": "2sHH5vCAY0IqxeDT1kfTx",
          "name": "Nome",
          "type": "VARCHAR",
          "default": "",
          "check": "",
          "primary": false,
          "unique": false,
          "notNull": true,
          "increment": false,
          "comment": "",
          "size": 60
        },
        {
          "id": "DuZ0fuyv6rdPfJsnIHJl8",
          "name": "Descricao",
          "type": "VARCHAR",
          "default": "",
          "check": "",
          "primary": false,
          "unique": false,
          "notNull": false,
          "increment": false,
          "comment": "",
          "size": 300
        }
      ],
      "comment": "",
      "indices": [],
      "color": "#175e7a"
    },
    {
      "id": "aBWlpOB18JuJ5b78sNkaR",
      "name": "Material",
      "x": 8.689332088620858,
      "y": 546.4946844382764,
      "locked": false,
      "fields": [
        {
          "name": "Id",
          "type": "SMALLINT",
          "default": "",
          "check": "",
          "primary": true,
          "unique": true,
          "notNull": true,
          "increment": true,
          "comment": "",
          "id": "WYbqbfPqPA4p6Wba83J1h",
          "size": "",
          "values": []
        },
        {
          "id": "q6V60Q_yy723W1JPYhcyf",
          "name": "IdCategoriaMaterial",
          "type": "TINYINT",
          "default": "",
          "check": "",
          "primary": false,
          "unique": false,
          "notNull": true,
          "increment": false,
          "comment": "",
          "size": "",
          "values": []
        },
        {
          "id": "58u--7ISyYU4dEn-BnwmW",
          "name": "IdFornecedor",
          "type": "TINYINT",
          "default": "",
          "check": "",
          "primary": false,
          "unique": false,
          "notNull": true,
          "increment": false,
          "comment": "",
          "size": "",
          "values": []
        },
        {
          "id": "MyKkWge20tMld3RHYOvHO",
          "name": "IdFabricante",
          "type": "TINYINT",
          "default": "",
          "check": "",
          "primary": false,
          "unique": false,
          "notNull": true,
          "increment": false,
          "comment": "",
          "size": "",
          "values": []
        },
        {
          "id": "GIKG94ElmS59YwhgxpeYV",
          "name": "IdLocalArmazenamento",
          "type": "TINYINT",
          "default": "",
          "check": "",
          "primary": false,
          "unique": false,
          "notNull": true,
          "increment": false,
          "comment": "",
          "size": "",
          "values": []
        },
        {
          "id": "Y2ZhWW5vww7b_KbW3rDzJ",
          "name": "UnidadeMedida",
          "type": "VARCHAR",
          "default": "",
          "check": "",
          "primary": false,
          "unique": false,
          "notNull": true,
          "increment": false,
          "comment": "",
          "size": 15,
          "values": []
        },
        {
          "id": "wLsu2zBnM-A0cvNCLNhSv",
          "name": "EstoqueAtual",
          "type": "SMALLINT",
          "default": "",
          "check": "CHECK ( EstoqueAtual < 10)",
          "primary": false,
          "unique": false,
          "notNull": true,
          "increment": false,
          "comment": "",
          "size": "",
          "values": []
        },
        {
          "id": "XeKWoSH9Q5hdvZ9QBOYo6",
          "name": "Nome",
          "type": "VARCHAR",
          "default": "",
          "check": "",
          "primary": false,
          "unique": false,
          "notNull": true,
          "increment": false,
          "comment": "",
          "size": 100
        },
        {
          "id": "_hv6rXgaAWmV9IvMmENmI",
          "name": "IdUsuarioUltimaAtualizacao",
          "type": "TINYINT",
          "default": "",
          "check": "",
          "primary": false,
          "unique": false,
          "notNull": false,
          "increment": false,
          "comment": "",
          "size": "",
          "values": []
        },
        {
          "id": "RG73Wwryhz-3GdBqmMFoE",
          "name": "DataUltimaAtualizacao",
          "type": "DATETIME",
          "default": "",
          "check": "",
          "primary": false,
          "unique": false,
          "notNull": false,
          "increment": false,
          "comment": "",
          "size": "",
          "values": []
        }
      ],
      "comment": "",
      "indices": [],
      "color": "#175e7a"
    },
    {
      "id": "fsp1yFjQ-XdTazrmfsIai",
      "name": "AtivoTi",
      "x": -1506.760852383723,
      "y": 821.3098361709392,
      "locked": false,
      "fields": [
        {
          "name": "Id",
          "type": "SMALLINT",
          "default": "",
          "check": "",
          "primary": true,
          "unique": true,
          "notNull": true,
          "increment": true,
          "comment": "",
          "id": "bN3VCb71zd3nMLAj359OM",
          "size": "",
          "values": []
        },
        {
          "id": "IiJZPQMFVOU42tTBr9ktQ",
          "name": "IdFornecedor",
          "type": "TINYINT",
          "default": "",
          "check": "",
          "primary": false,
          "unique": false,
          "notNull": true,
          "increment": false,
          "comment": "",
          "size": "",
          "values": []
        },
        {
          "id": "6iF_gZrIZ30WFneSBtPtt",
          "name": "IdFabricante",
          "type": "TINYINT",
          "default": "",
          "check": "",
          "primary": false,
          "unique": false,
          "notNull": true,
          "increment": false,
          "comment": "",
          "size": "",
          "values": []
        },
        {
          "id": "JFHaFna4r_FrCzsNtmDQl",
          "name": "IdCategoriaAtivo",
          "type": "TINYINT",
          "default": "",
          "check": "",
          "primary": false,
          "unique": false,
          "notNull": true,
          "increment": false,
          "comment": "",
          "size": "",
          "values": []
        },
        {
          "id": "N42AvUJsJ6APm3u1DG3-Q",
          "name": "IdStatusAtivo",
          "type": "TINYINT",
          "default": "",
          "check": "",
          "primary": false,
          "unique": false,
          "notNull": true,
          "increment": false,
          "comment": "",
          "size": "",
          "values": []
        },
        {
          "id": "Lij5OB6xRp5ZdTRkrcIzD",
          "name": "Nome",
          "type": "VARCHAR",
          "default": "",
          "check": "",
          "primary": false,
          "unique": false,
          "notNull": true,
          "increment": false,
          "comment": "",
          "size": 100
        },
        {
          "id": "jjsbFVHH8vZhEECIZESJ5",
          "name": "CodigoPatrimonio",
          "type": "VARCHAR",
          "default": "",
          "check": "",
          "primary": false,
          "unique": false,
          "notNull": true,
          "increment": false,
          "comment": "",
          "size": 9,
          "values": []
        },
        {
          "id": "iFvVvwlBQaq4K9jEJbgan",
          "name": "NumeroSerie",
          "type": "VARCHAR",
          "default": "",
          "check": "",
          "primary": false,
          "unique": false,
          "notNull": true,
          "increment": false,
          "comment": "",
          "size": 17,
          "values": []
        },
        {
          "id": "3eV4Kr46dAiFPTeHX_2T3",
          "name": "DataAquisicao",
          "type": "DATETIME",
          "default": "",
          "check": "",
          "primary": false,
          "unique": false,
          "notNull": true,
          "increment": false,
          "comment": "",
          "size": "",
          "values": []
        },
        {
          "id": "1Ee7aeAjaflun3QXV8s9g",
          "name": "ValorAquisicao",
          "type": "DECIMAL",
          "default": "",
          "check": "",
          "primary": false,
          "unique": false,
          "notNull": true,
          "increment": false,
          "comment": "",
          "size": "10,2"
        },
        {
          "id": "J4IidqNMo3NFNSmZUkly_",
          "name": "DataFimGarantia",
          "type": "DATE",
          "default": "",
          "check": "",
          "primary": false,
          "unique": false,
          "notNull": true,
          "increment": false,
          "comment": "",
          "size": "",
          "values": []
        },
        {
          "id": "pMwa8movssDFSFhAER1-E",
          "name": "IdUsuarioUltimaAtualizacao",
          "type": "TINYINT",
          "default": "",
          "check": "",
          "primary": false,
          "unique": false,
          "notNull": false,
          "increment": false,
          "comment": "",
          "size": "",
          "values": []
        },
        {
          "id": "PIbF0vE3oNyFPKpLX5ijV",
          "name": "DataUltimaAtualizacao",
          "type": "DATETIME",
          "default": "",
          "check": "",
          "primary": false,
          "unique": false,
          "notNull": false,
          "increment": false,
          "comment": "",
          "size": "",
          "values": []
        }
      ],
      "comment": "",
      "indices": [],
      "color": "#175e7a"
    },
    {
      "id": "mde5pecJ6T77z9pMnLM-f",
      "name": "LogAuditoria",
      "x": 2223.796325089047,
      "y": -1180.4703325483576,
      "locked": false,
      "fields": [
        {
          "name": "Id",
          "type": "INTEGER",
          "default": "",
          "check": "",
          "primary": true,
          "unique": true,
          "notNull": true,
          "increment": true,
          "comment": "",
          "id": "E-Gfb-SfQFCOcIzzf_q_7"
        },
        {
          "id": "p_yjxXp06uDpdrs9XcZEg",
          "name": "IdUsuario",
          "type": "INTEGER",
          "default": "",
          "check": "",
          "primary": false,
          "unique": false,
          "notNull": true,
          "increment": false,
          "comment": "",
          "size": "",
          "values": []
        },
        {
          "id": "JkYMeM-hq-dSushVm6AN6",
          "name": "TabelaAfetada",
          "type": "VARCHAR",
          "default": "",
          "check": "",
          "primary": false,
          "unique": false,
          "notNull": true,
          "increment": false,
          "comment": "",
          "size": 60
        },
        {
          "id": "-tObR3tIcdDniv3l9RQEJ",
          "name": "IdRegistroAfetado",
          "type": "INTEGER",
          "default": "",
          "check": "",
          "primary": false,
          "unique": false,
          "notNull": true,
          "increment": false,
          "comment": "",
          "size": "",
          "values": []
        },
        {
          "id": "lurGey6RDE4dOwNQOKWUa",
          "name": "DataHoraAlteracao",
          "type": "DATETIME",
          "default": "",
          "check": "",
          "primary": false,
          "unique": false,
          "notNull": true,
          "increment": false,
          "comment": "",
          "size": "",
          "values": []
        },
        {
          "id": "mzLENmNYkHj5x9tPUH0Xd",
          "name": "Detalhes",
          "type": "VARCHAR",
          "default": "",
          "check": "",
          "primary": false,
          "unique": false,
          "notNull": false,
          "increment": false,
          "comment": "",
          "size": 300
        }
      ],
      "comment": "",
      "indices": [],
      "color": "#175e7a"
    },
    {
      "id": "zc7H9Y8soiQeTcc4fTm89",
      "name": "PerfilAcesso",
      "x": 549.279201677137,
      "y": -1130.1129522934173,
      "locked": false,
      "fields": [
        {
          "name": "Id",
          "type": "TINYINT",
          "default": "",
          "check": "",
          "primary": true,
          "unique": true,
          "notNull": true,
          "increment": true,
          "comment": "",
          "id": "cZNDs_qQtgxtLRbQUKOTD",
          "size": "",
          "values": []
        },
        {
          "id": "OJgoS7dvi2XgEPs5fgFmL",
          "name": "Nome",
          "type": "VARCHAR",
          "default": "",
          "check": "",
          "primary": false,
          "unique": false,
          "notNull": true,
          "increment": false,
          "comment": "",
          "size": 80
        },
        {
          "id": "WBd2bTLPEV7437a_F369m",
          "name": "Descricao",
          "type": "VARCHAR",
          "default": "",
          "check": "",
          "primary": false,
          "unique": false,
          "notNull": false,
          "increment": false,
          "comment": "",
          "size": 300
        }
      ],
      "comment": "",
      "indices": [],
      "color": "#175e7a"
    },
    {
      "id": "ak3771Fu2ptjVOratO2wd",
      "name": "StatusAtivo",
      "x": -2310.4736130948772,
      "y": 1245.9726452645202,
      "locked": false,
      "fields": [
        {
          "name": "Id",
          "type": "TINYINT",
          "default": "",
          "check": "",
          "primary": true,
          "unique": true,
          "notNull": true,
          "increment": true,
          "comment": "",
          "id": "vbm2hqmxuk8hvyFh9j6EO",
          "size": "",
          "values": []
        },
        {
          "id": "ZhK-s0Dm0gWul_4ozW6Q4",
          "name": "Nome",
          "type": "VARCHAR",
          "default": "",
          "check": "",
          "primary": false,
          "unique": false,
          "notNull": true,
          "increment": false,
          "comment": "",
          "size": 30
        }
      ],
      "comment": "",
      "indices": [],
      "color": "#175e7a"
    },
    {
      "id": "HtsAoWFNkTrkz7_Juc-6E",
      "name": "Fornecedor",
      "x": -879.293199556476,
      "y": 214.99074047038619,
      "locked": false,
      "fields": [
        {
          "name": "Id",
          "type": "TINYINT",
          "default": "",
          "check": "",
          "primary": true,
          "unique": true,
          "notNull": true,
          "increment": true,
          "comment": "",
          "id": "jM4JWcG2PkFUT-l6RFD4O",
          "size": "",
          "values": []
        },
        {
          "id": "hjfK2-rQLTBgKCu4ME88p",
          "name": "Nome",
          "type": "VARCHAR",
          "default": "",
          "check": "",
          "primary": false,
          "unique": false,
          "notNull": true,
          "increment": false,
          "comment": "",
          "size": 100
        },
        {
          "id": "6tqLBjiU4kwrPnRXxvNs5",
          "name": "Cnpj",
          "type": "CHAR",
          "default": "",
          "check": "",
          "primary": false,
          "unique": true,
          "notNull": true,
          "increment": false,
          "comment": "",
          "size": 14
        },
        {
          "id": "PY_iKZjt5Ek6dKsqp5BOm",
          "name": "Telefone",
          "type": "CHAR",
          "default": "",
          "check": "",
          "primary": false,
          "unique": false,
          "notNull": true,
          "increment": false,
          "comment": "",
          "size": 11
        },
        {
          "id": "7wX8uTB4aocrF8mHwamer",
          "name": "Email",
          "type": "VARCHAR",
          "default": "",
          "check": "",
          "primary": false,
          "unique": false,
          "notNull": true,
          "increment": false,
          "comment": "",
          "size": 160
        },
        {
          "id": "cQNv6iFiqGoWUEzxbfa9j",
          "name": "DataCadastro",
          "type": "DATE",
          "default": "",
          "check": "",
          "primary": false,
          "unique": false,
          "notNull": true,
          "increment": false,
          "comment": "",
          "size": "",
          "values": []
        },
        {
          "id": "dkKLOlceDc-iZCn0SU2dB",
          "name": "Descricao",
          "type": "VARCHAR",
          "default": "",
          "check": "",
          "primary": false,
          "unique": false,
          "notNull": false,
          "increment": false,
          "comment": "",
          "size": 300
        },
        {
          "id": "Y-32a3VS8UQlrLAZ_tZYw",
          "name": "IdUsuarioUltimaAtualizacao",
          "type": "TINYINT",
          "default": "",
          "check": "",
          "primary": false,
          "unique": false,
          "notNull": false,
          "increment": false,
          "comment": "",
          "size": "",
          "values": []
        },
        {
          "id": "rx0EV4V4suIaY-rarjXY8",
          "name": "DataUltimaAtualizacao",
          "type": "DATETIME",
          "default": "",
          "check": "",
          "primary": false,
          "unique": false,
          "notNull": false,
          "increment": false,
          "comment": "",
          "size": "",
          "values": []
        }
      ],
      "comment": "",
      "indices": [],
      "color": "#175e7a"
    },
    {
      "id": "cga3L75g1v60KgiLIKTjd",
      "name": "Fabricante",
      "x": -879.2784567742625,
      "y": 985.8813309406482,
      "locked": false,
      "fields": [
        {
          "name": "Id",
          "type": "TINYINT",
          "default": "",
          "check": "",
          "primary": true,
          "unique": true,
          "notNull": true,
          "increment": true,
          "comment": "",
          "id": "J-Qtd60sYmmN5an_IUNsz",
          "size": "",
          "values": []
        },
        {
          "id": "OZG7-_hA5IwXROQ6HC_iy",
          "name": "Nome",
          "type": "VARCHAR",
          "default": "",
          "check": "",
          "primary": false,
          "unique": false,
          "notNull": true,
          "increment": false,
          "comment": "",
          "size": 100
        },
        {
          "id": "OlNZku_PAZqmR6S-1oI5c",
          "name": "Cnpj",
          "type": "CHAR",
          "default": "",
          "check": "",
          "primary": false,
          "unique": true,
          "notNull": true,
          "increment": false,
          "comment": "",
          "size": 14
        },
        {
          "id": "yKndINwwP0kCQAIIQBY9c",
          "name": "Telefone",
          "type": "CHAR",
          "default": "",
          "check": "",
          "primary": false,
          "unique": false,
          "notNull": true,
          "increment": false,
          "comment": "",
          "size": 11
        },
        {
          "id": "nOnMuI1iLW4fXz1wjOG5p",
          "name": "Email",
          "type": "VARCHAR",
          "default": "",
          "check": "",
          "primary": false,
          "unique": false,
          "notNull": true,
          "increment": false,
          "comment": "",
          "size": 160
        },
        {
          "id": "AwyYYe8JGm0SAI2DcisQi",
          "name": "DataCadastro",
          "type": "DATE",
          "default": "",
          "check": "",
          "primary": false,
          "unique": false,
          "notNull": true,
          "increment": false,
          "comment": "",
          "size": "",
          "values": []
        },
        {
          "id": "F8FbBpeXDY4rzchtw2FGw",
          "name": "Descricao",
          "type": "VARCHAR",
          "default": "",
          "check": "",
          "primary": false,
          "unique": false,
          "notNull": false,
          "increment": false,
          "comment": "",
          "size": 300
        },
        {
          "id": "zppn6ipkI9s9bQUIqg49w",
          "name": "IdUsuarioUltimaAtualizacao",
          "type": "TINYINT",
          "default": "",
          "check": "",
          "primary": false,
          "unique": false,
          "notNull": false,
          "increment": false,
          "comment": "",
          "size": "",
          "values": []
        },
        {
          "id": "XLEBw8efpjDi2iLtT9lIR",
          "name": "DataUltimaAtualizacao",
          "type": "DATETIME",
          "default": "",
          "check": "",
          "primary": false,
          "unique": false,
          "notNull": false,
          "increment": false,
          "comment": "",
          "size": "",
          "values": []
        }
      ],
      "comment": "",
      "indices": [],
      "color": "#175e7a"
    },
    {
      "id": "2N-HOqfSqEfSoYRTxI32h",
      "name": "MovimentacaoAtivoTi",
      "x": -1782.1295591033283,
      "y": -543.540388464472,
      "locked": false,
      "fields": [
        {
          "name": "Id",
          "type": "INTEGER",
          "default": "",
          "check": "",
          "primary": true,
          "unique": true,
          "notNull": true,
          "increment": true,
          "comment": "",
          "id": "S-snYCLpgdntU98e8V5Pc"
        },
        {
          "id": "gVBC-pSXzhT65M-HmrHpa",
          "name": "IdUsuarioSolicitante",
          "type": "TINYINT",
          "default": "",
          "check": "",
          "primary": false,
          "unique": false,
          "notNull": true,
          "increment": false,
          "comment": "",
          "size": "",
          "values": []
        },
        {
          "id": "Yg1WQ67JEJvKA4j1dFkJH",
          "name": "IdTipoMovimentacao",
          "type": "TINYINT",
          "default": "",
          "check": "",
          "primary": false,
          "unique": false,
          "notNull": true,
          "increment": false,
          "comment": "",
          "size": "",
          "values": []
        },
        {
          "id": "IctnJuTacfy3FDG3Hemt_",
          "name": "IdColaboradorOrigem",
          "type": "SMALLINT",
          "default": "",
          "check": "",
          "primary": false,
          "unique": false,
          "notNull": false,
          "increment": false,
          "comment": "",
          "size": "",
          "values": []
        },
        {
          "id": "xJ9flwQfxtGLb9VxHJHSj",
          "name": "IdAtivoTi",
          "type": "SMALLINT",
          "default": "",
          "check": "",
          "primary": false,
          "unique": false,
          "notNull": true,
          "increment": false,
          "comment": "",
          "size": "",
          "values": []
        },
        {
          "id": "TQ2ILMkD6ITHwxrgknVP_",
          "name": "DataMovimentacao",
          "type": "DATETIME",
          "default": "",
          "check": "",
          "primary": false,
          "unique": false,
          "notNull": true,
          "increment": false,
          "comment": "",
          "size": "",
          "values": []
        },
        {
          "id": "xT1jxPlTL5PB2qFEJEJr3",
          "name": "Justificativa",
          "type": "VARCHAR",
          "default": "",
          "check": "",
          "primary": false,
          "unique": false,
          "notNull": true,
          "increment": false,
          "comment": "",
          "size": 500
        },
        {
          "id": "kcO2xzLQ0kKD9MTesuwki",
          "name": "Quantidade",
          "type": "SMALLINT",
          "default": "",
          "check": "",
          "primary": false,
          "unique": false,
          "notNull": true,
          "increment": false,
          "comment": "",
          "size": "",
          "values": []
        },
        {
          "id": "fUPromDNDojEv2zwNmxz2",
          "name": "IdUsuarioUltimaAtualizacao",
          "type": "TINYINT",
          "default": "",
          "check": "",
          "primary": false,
          "unique": false,
          "notNull": false,
          "increment": false,
          "comment": "",
          "size": "",
          "values": []
        },
        {
          "id": "Ync6ZfaOtCRJbBERqUpNF",
          "name": "DataUltimaAtualizacao",
          "type": "DATETIME",
          "default": "",
          "check": "",
          "primary": false,
          "unique": false,
          "notNull": false,
          "increment": false,
          "comment": "",
          "size": "",
          "values": []
        }
      ],
      "comment": "",
      "indices": [],
      "color": "#175e7a"
    },
    {
      "id": "bNkXIkD8qywTcERWWe_OZ",
      "name": "TipoMovimentacao",
      "x": -909.0025908263343,
      "y": -423.818716434479,
      "locked": false,
      "fields": [
        {
          "name": "Id",
          "type": "TINYINT",
          "default": "",
          "check": "",
          "primary": true,
          "unique": true,
          "notNull": true,
          "increment": true,
          "comment": "",
          "id": "kA_WYAJdw7TQsRRskmQdX",
          "size": "",
          "values": []
        },
        {
          "id": "2kyZ3wEy9GmbVcmveDW1Y",
          "name": "Nome",
          "type": "VARCHAR",
          "default": "",
          "check": "",
          "primary": false,
          "unique": false,
          "notNull": true,
          "increment": false,
          "comment": "",
          "size": 30
        }
      ],
      "comment": "",
      "indices": [],
      "color": "#175e7a"
    },
    {
      "id": "hd5AT7xd6BUxpZhRIueLX",
      "name": "LicencaSoftware",
      "x": -3097.3477638703534,
      "y": 677.9003077866885,
      "locked": false,
      "fields": [
        {
          "name": "Id",
          "type": "SMALLINT",
          "default": "",
          "check": "",
          "primary": true,
          "unique": true,
          "notNull": true,
          "increment": true,
          "comment": "",
          "id": "YH7RUEI5Yy-m5KyyQVYt0",
          "size": "",
          "values": []
        },
        {
          "id": "FoczeTqfPp4yME2qNywlr",
          "name": "Nome",
          "type": "VARCHAR",
          "default": "",
          "check": "",
          "primary": false,
          "unique": false,
          "notNull": true,
          "increment": false,
          "comment": "",
          "size": 80
        }
      ],
      "comment": "",
      "indices": [],
      "color": "#175e7a"
    },
    {
      "id": "t5aMI4CHFSkXJbsvnD76G",
      "name": "LicencaSoftwareAtivoTi",
      "x": -2340.6931320711583,
      "y": 346.27405057495287,
      "locked": false,
      "fields": [
        {
          "id": "MPeQKh2_V3L8tesO40FVu",
          "name": "IdAtivoTi",
          "type": "SMALLINT",
          "default": "",
          "check": "",
          "primary": true,
          "unique": false,
          "notNull": true,
          "increment": false,
          "comment": "",
          "size": "",
          "values": []
        },
        {
          "name": "IdLicencaSoftware",
          "type": "SMALLINT",
          "default": "",
          "check": "",
          "primary": true,
          "unique": false,
          "notNull": true,
          "increment": false,
          "comment": "",
          "id": "UXsaAbmeLEzAx_Sqo5J8D",
          "size": "",
          "values": []
        },
        {
          "id": "srePpqA0RDDbd4AxIlrrr",
          "name": "ChaveProduto",
          "type": "VARCHAR",
          "default": "",
          "check": "",
          "primary": false,
          "unique": false,
          "notNull": true,
          "increment": false,
          "comment": "",
          "size": 100
        },
        {
          "id": "4GOUYSSDmUaJPxvmt_NAz",
          "name": "DataExpiracao",
          "type": "DATE",
          "default": "",
          "check": "",
          "primary": false,
          "unique": false,
          "notNull": false,
          "increment": false,
          "comment": "",
          "size": "",
          "values": []
        }
      ],
      "comment": "",
      "indices": [],
      "color": "#175e7a"
    },
    {
      "id": "pD68Mr-bmGLwcxoPA3Rq1",
      "name": "Manutencao",
      "x": -2480.9180908007925,
      "y": 653.6860290889297,
      "locked": false,
      "fields": [
        {
          "name": "Id",
          "type": "INTEGER",
          "default": "",
          "check": "",
          "primary": true,
          "unique": true,
          "notNull": true,
          "increment": true,
          "comment": "",
          "id": "IV8ceE0Y_5b5w4qsJL9gb"
        },
        {
          "id": "88Ntn2dojiyGSWUiLlgRN",
          "name": "IdAtivoTi",
          "type": "SMALLINT",
          "default": "",
          "check": "",
          "primary": false,
          "unique": false,
          "notNull": true,
          "increment": false,
          "comment": "",
          "size": "",
          "values": []
        },
        {
          "id": "VPzRJpEzWwSbTIr6XJ04i",
          "name": "Preventiva",
          "type": "BIT",
          "default": "",
          "check": "",
          "primary": false,
          "unique": false,
          "notNull": true,
          "increment": false,
          "comment": "",
          "values": []
        },
        {
          "id": "OrdL5YEEGDIGHiKS2sgbN",
          "name": "DataInicio",
          "type": "DATE",
          "default": "",
          "check": "",
          "primary": false,
          "unique": false,
          "notNull": true,
          "increment": false,
          "comment": "",
          "size": "",
          "values": []
        },
        {
          "id": "AsKt_P7nE7pajborpRApC",
          "name": "DataFim",
          "type": "DATE",
          "default": "",
          "check": "",
          "primary": false,
          "unique": false,
          "notNull": true,
          "increment": false,
          "comment": "",
          "size": "",
          "values": []
        },
        {
          "id": "PPkZ9WVaPqX6SgG9nT-Yo",
          "name": "DescricaoProblema",
          "type": "VARCHAR",
          "default": "",
          "check": "",
          "primary": false,
          "unique": false,
          "notNull": true,
          "increment": false,
          "comment": "",
          "size": 1000
        },
        {
          "id": "BwfRTp1rCzdoho3iMt_w9",
          "name": "DescricaoServicoRealizado",
          "type": "VARCHAR",
          "default": "",
          "check": "",
          "primary": false,
          "unique": false,
          "notNull": true,
          "increment": false,
          "comment": "",
          "size": 1000
        },
        {
          "id": "zzs9rhYc4w37N4wjtvAWc",
          "name": "Custo",
          "type": "DECIMAL",
          "default": "",
          "check": "",
          "primary": false,
          "unique": false,
          "notNull": true,
          "increment": false,
          "comment": "",
          "size": "10,2"
        },
        {
          "id": "3OCmbMJW7C20jtUg6355A",
          "name": "IdUsuarioUltimaAtualizacao",
          "type": "TINYINT",
          "default": "",
          "check": "",
          "primary": false,
          "unique": false,
          "notNull": false,
          "increment": false,
          "comment": "",
          "size": "",
          "values": []
        },
        {
          "id": "KOjuj7TsQp7ZvAXw00NoY",
          "name": "DataUltimaAtualizacao",
          "type": "DATETIME",
          "default": "",
          "check": "",
          "primary": false,
          "unique": false,
          "notNull": false,
          "increment": false,
          "comment": "",
          "size": "",
          "values": []
        }
      ],
      "comment": "",
      "indices": [],
      "color": "#175e7a"
    },
    {
      "id": "LUbGySKHkY0I1BMrcfDN8",
      "name": "CategoriaMaterial",
      "x": 552.8910303888408,
      "y": 301.7185494101444,
      "locked": false,
      "fields": [
        {
          "name": "Id",
          "type": "TINYINT",
          "default": "",
          "check": "",
          "primary": true,
          "unique": true,
          "notNull": true,
          "increment": true,
          "comment": "",
          "id": "O0L4ND1WRkC3V54Eny0SK",
          "size": "",
          "values": []
        },
        {
          "id": "gdxYxgWfAbUTzWKfEhVOW",
          "name": "Nome",
          "type": "VARCHAR",
          "default": "",
          "check": "",
          "primary": false,
          "unique": false,
          "notNull": true,
          "increment": false,
          "comment": "",
          "size": 30
        }
      ],
      "comment": "",
      "indices": [],
      "color": "#175e7a"
    },
    {
      "id": "V1uYTvmyCCvrwvekE2jwC",
      "name": "LocalArmazenamento",
      "x": 582.1677115518958,
      "y": 1118.892829625928,
      "locked": false,
      "fields": [
        {
          "name": "Id",
          "type": "TINYINT",
          "default": "",
          "check": "",
          "primary": true,
          "unique": true,
          "notNull": true,
          "increment": true,
          "comment": "",
          "id": "Uf94pu17bwlbpd2WKo7LO",
          "size": "",
          "values": []
        },
        {
          "id": "i586wq4WDo_njNkuBDcNi",
          "name": "Nome",
          "type": "VARCHAR",
          "default": "",
          "check": "",
          "primary": false,
          "unique": false,
          "notNull": true,
          "increment": false,
          "comment": "",
          "size": 40
        }
      ],
      "comment": "",
      "indices": [],
      "color": "#175e7a"
    },
    {
      "id": "40yak4QOnCAlDlG0q_Ny0",
      "name": "StatusUsuario",
      "x": 109.50175808884558,
      "y": -890.4604859768841,
      "locked": false,
      "fields": [
        {
          "name": "Id",
          "type": "TINYINT",
          "default": "",
          "check": "",
          "primary": true,
          "unique": true,
          "notNull": true,
          "increment": true,
          "comment": "",
          "id": "jPfcYfL6rHLpbCXb-LFxw",
          "size": "",
          "values": []
        },
        {
          "id": "3RjkpYB8XIM7uyKE0A0yQ",
          "name": "Nome",
          "type": "VARCHAR",
          "default": "",
          "check": "",
          "primary": false,
          "unique": false,
          "notNull": true,
          "increment": false,
          "comment": "",
          "size": 30
        }
      ],
      "comment": "",
      "indices": [],
      "color": "#175e7a"
    },
    {
      "id": "6FsKnstHqrRoB-0MZ9WsS",
      "name": "Sala",
      "x": -3069.3537740220463,
      "y": 343.7422722289032,
      "locked": false,
      "fields": [
        {
          "name": "Id",
          "type": "TINYINT",
          "default": "",
          "check": "",
          "primary": true,
          "unique": true,
          "notNull": true,
          "increment": true,
          "comment": "",
          "id": "NaVTvkJ3bxoLZj_s4VRd8",
          "size": "",
          "values": []
        },
        {
          "id": "u5dVmJ0xyaWsbsVuEa-BS",
          "name": "IdFilial",
          "type": "TINYINT",
          "default": "",
          "check": "",
          "primary": false,
          "unique": false,
          "notNull": true,
          "increment": false,
          "comment": "",
          "size": "",
          "values": []
        },
        {
          "id": "WBtH2i-X23gbLPHGjLn85",
          "name": "Nome",
          "type": "VARCHAR",
          "default": "",
          "check": "",
          "primary": false,
          "unique": false,
          "notNull": true,
          "increment": false,
          "comment": "",
          "size": 80
        },
        {
          "id": "pEhDHst68PHq22AtF8fAE",
          "name": "Descricao",
          "type": "VARCHAR",
          "default": "",
          "check": "",
          "primary": false,
          "unique": false,
          "notNull": false,
          "increment": false,
          "comment": "",
          "size": 300
        }
      ],
      "comment": "",
      "indices": [],
      "color": "#175e7a"
    }
  ],
  "relationships": [
    {
      "startTableId": "l-UUUMGmE5jh0crDWddKS",
      "startFieldId": "HdHStf7sU7DSR2zhTqmKV",
      "endTableId": "aMedcj3vxJ6c6Txe6vQ2h",
      "endFieldId": "zdw1qx4GesWHtx-Ygrhm9",
      "cardinality": "one_to_many",
      "updateConstraint": "No action",
      "deleteConstraint": "No action",
      "name": "FK_Filial_Colaborador",
      "id": 0
    },
    {
      "startTableId": "ak3771Fu2ptjVOratO2wd",
      "startFieldId": "vbm2hqmxuk8hvyFh9j6EO",
      "endTableId": "fsp1yFjQ-XdTazrmfsIai",
      "endFieldId": "N42AvUJsJ6APm3u1DG3-Q",
      "cardinality": "one_to_many",
      "updateConstraint": "No action",
      "deleteConstraint": "No action",
      "name": "FK_StatusAtivo_AtivoTi",
      "id": 1
    },
    {
      "startTableId": "cga3L75g1v60KgiLIKTjd",
      "startFieldId": "J-Qtd60sYmmN5an_IUNsz",
      "endTableId": "fsp1yFjQ-XdTazrmfsIai",
      "endFieldId": "6iF_gZrIZ30WFneSBtPtt",
      "cardinality": "one_to_many",
      "updateConstraint": "No action",
      "deleteConstraint": "No action",
      "name": "FK_Fabricante_AtivoTi",
      "id": 2
    },
    {
      "startTableId": "znT_6XPvYhsgtcjSti49b",
      "startFieldId": "-ds9J9h4tE4R1HXNEE9lL",
      "endTableId": "fsp1yFjQ-XdTazrmfsIai",
      "endFieldId": "JFHaFna4r_FrCzsNtmDQl",
      "cardinality": "one_to_many",
      "updateConstraint": "No action",
      "deleteConstraint": "No action",
      "name": "FK_CategoriaAtivo_AtivoTi",
      "id": 3
    },
    {
      "startTableId": "HtsAoWFNkTrkz7_Juc-6E",
      "startFieldId": "jM4JWcG2PkFUT-l6RFD4O",
      "endTableId": "fsp1yFjQ-XdTazrmfsIai",
      "endFieldId": "IiJZPQMFVOU42tTBr9ktQ",
      "cardinality": "one_to_many",
      "updateConstraint": "No action",
      "deleteConstraint": "No action",
      "name": "FK_Fornecedor_AtivoTi",
      "id": 4
    },
    {
      "startTableId": "bNkXIkD8qywTcERWWe_OZ",
      "startFieldId": "kA_WYAJdw7TQsRRskmQdX",
      "endTableId": "2N-HOqfSqEfSoYRTxI32h",
      "endFieldId": "Yg1WQ67JEJvKA4j1dFkJH",
      "cardinality": "one_to_many",
      "updateConstraint": "No action",
      "deleteConstraint": "No action",
      "name": "FK_TipoMovimentacao_MovimentacaoAtivoTi",
      "id": 6
    },
    {
      "startTableId": "fsp1yFjQ-XdTazrmfsIai",
      "startFieldId": "bN3VCb71zd3nMLAj359OM",
      "endTableId": "t5aMI4CHFSkXJbsvnD76G",
      "endFieldId": "MPeQKh2_V3L8tesO40FVu",
      "cardinality": "one_to_many",
      "updateConstraint": "No action",
      "deleteConstraint": "No action",
      "name": "FK_AtivoTi_LicencaAtivo",
      "id": 7
    },
    {
      "startTableId": "hd5AT7xd6BUxpZhRIueLX",
      "startFieldId": "YH7RUEI5Yy-m5KyyQVYt0",
      "endTableId": "t5aMI4CHFSkXJbsvnD76G",
      "endFieldId": "UXsaAbmeLEzAx_Sqo5J8D",
      "cardinality": "one_to_many",
      "updateConstraint": "No action",
      "deleteConstraint": "No action",
      "name": "FK_LicencaSoftware_LicencaSoftwareAtivoTi",
      "id": 8
    },
    {
      "startTableId": "fsp1yFjQ-XdTazrmfsIai",
      "startFieldId": "bN3VCb71zd3nMLAj359OM",
      "endTableId": "pD68Mr-bmGLwcxoPA3Rq1",
      "endFieldId": "88Ntn2dojiyGSWUiLlgRN",
      "cardinality": "one_to_many",
      "updateConstraint": "No action",
      "deleteConstraint": "No action",
      "name": "FK_AtivoTi_Manutencao",
      "id": 9
    },
    {
      "startTableId": "LUbGySKHkY0I1BMrcfDN8",
      "startFieldId": "O0L4ND1WRkC3V54Eny0SK",
      "endTableId": "aBWlpOB18JuJ5b78sNkaR",
      "endFieldId": "q6V60Q_yy723W1JPYhcyf",
      "cardinality": "one_to_many",
      "updateConstraint": "No action",
      "deleteConstraint": "No action",
      "name": "FK_CategoriaMaterial_Material",
      "id": 10
    },
    {
      "startTableId": "cga3L75g1v60KgiLIKTjd",
      "startFieldId": "J-Qtd60sYmmN5an_IUNsz",
      "endTableId": "aBWlpOB18JuJ5b78sNkaR",
      "endFieldId": "MyKkWge20tMld3RHYOvHO",
      "cardinality": "one_to_many",
      "updateConstraint": "No action",
      "deleteConstraint": "No action",
      "name": "FK_Fabricante_Material",
      "id": 11
    },
    {
      "startTableId": "HtsAoWFNkTrkz7_Juc-6E",
      "startFieldId": "jM4JWcG2PkFUT-l6RFD4O",
      "endTableId": "aBWlpOB18JuJ5b78sNkaR",
      "endFieldId": "58u--7ISyYU4dEn-BnwmW",
      "cardinality": "one_to_many",
      "updateConstraint": "No action",
      "deleteConstraint": "No action",
      "name": "FK_Fornecedor_Material",
      "id": 12
    },
    {
      "startTableId": "Y453M_v1rTjDrkxgymu9e",
      "startFieldId": "hYKj0byaYCzCvgYaRDARP",
      "endTableId": "aMedcj3vxJ6c6Txe6vQ2h",
      "endFieldId": "e3J5JtnhTirfMvNoFVxV-",
      "cardinality": "one_to_many",
      "updateConstraint": "No action",
      "deleteConstraint": "No action",
      "name": "FK_Departamento_Colaborador",
      "id": 13
    },
    {
      "startTableId": "EgUBOf4V3YIqSYCglNDwm",
      "startFieldId": "oTb24hApjtLd3cIZlBWuG",
      "endTableId": "2N-HOqfSqEfSoYRTxI32h",
      "endFieldId": "gVBC-pSXzhT65M-HmrHpa",
      "cardinality": "one_to_many",
      "updateConstraint": "No action",
      "deleteConstraint": "No action",
      "name": "FK_Usuario_MovimentacaoAtivoTi",
      "id": 14
    },
    {
      "startTableId": "fsp1yFjQ-XdTazrmfsIai",
      "startFieldId": "bN3VCb71zd3nMLAj359OM",
      "endTableId": "2N-HOqfSqEfSoYRTxI32h",
      "endFieldId": "xJ9flwQfxtGLb9VxHJHSj",
      "cardinality": "one_to_many",
      "updateConstraint": "No action",
      "deleteConstraint": "No action",
      "name": "FK_AtivoTi_MovimentacaoAtivoTi",
      "id": 15
    },
    {
      "startTableId": "aMedcj3vxJ6c6Txe6vQ2h",
      "startFieldId": "2M58dRGLJvoEwgvr-PLJL",
      "endTableId": "2N-HOqfSqEfSoYRTxI32h",
      "endFieldId": "IctnJuTacfy3FDG3Hemt_",
      "cardinality": "one_to_many",
      "updateConstraint": "No action",
      "deleteConstraint": "No action",
      "name": "FK_ColaboradorOrigem_MovimentacaoAtivoTi",
      "id": 16
    },
    {
      "startTableId": "V1uYTvmyCCvrwvekE2jwC",
      "startFieldId": "Uf94pu17bwlbpd2WKo7LO",
      "endTableId": "aBWlpOB18JuJ5b78sNkaR",
      "endFieldId": "GIKG94ElmS59YwhgxpeYV",
      "cardinality": "one_to_many",
      "updateConstraint": "No action",
      "deleteConstraint": "No action",
      "name": "FK_LocalArmazenamento_Material",
      "id": 17
    },
    {
      "startTableId": "Bq7tOrufYBTd8Bgx2MM3E",
      "startFieldId": "xF8K_mMqHlH3wOsJpk35v",
      "endTableId": "aMedcj3vxJ6c6Txe6vQ2h",
      "endFieldId": "jgGtoUBpNDX6t6tSVhBBP",
      "cardinality": "one_to_many",
      "updateConstraint": "No action",
      "deleteConstraint": "No action",
      "name": "FK_Cargo_Colaborador",
      "id": 18
    },
    {
      "startTableId": "aBWlpOB18JuJ5b78sNkaR",
      "startFieldId": "WYbqbfPqPA4p6Wba83J1h",
      "endTableId": "aLe-2QywIxjXoM77qsWLM",
      "endFieldId": "pMPR5N5KOpCy1a_dMaTJx",
      "cardinality": "one_to_many",
      "updateConstraint": "No action",
      "deleteConstraint": "No action",
      "name": "FK_Material_MovimentacaoMaterial",
      "id": 19
    },
    {
      "startTableId": "bNkXIkD8qywTcERWWe_OZ",
      "startFieldId": "kA_WYAJdw7TQsRRskmQdX",
      "endTableId": "aLe-2QywIxjXoM77qsWLM",
      "endFieldId": "Yg1WQ67JEJvKA4j1dFkJH",
      "cardinality": "one_to_many",
      "updateConstraint": "No action",
      "deleteConstraint": "No action",
      "name": "FK_TipoMovimentacao_MovimentacaoMaterial",
      "id": 20
    },
    {
      "startTableId": "aMedcj3vxJ6c6Txe6vQ2h",
      "startFieldId": "2M58dRGLJvoEwgvr-PLJL",
      "endTableId": "aLe-2QywIxjXoM77qsWLM",
      "endFieldId": "IctnJuTacfy3FDG3Hemt_",
      "cardinality": "one_to_many",
      "updateConstraint": "No action",
      "deleteConstraint": "No action",
      "name": "FK_Colaborador_MovimentacaoMaterial",
      "id": 21
    },
    {
      "startTableId": "EgUBOf4V3YIqSYCglNDwm",
      "startFieldId": "oTb24hApjtLd3cIZlBWuG",
      "endTableId": "aLe-2QywIxjXoM77qsWLM",
      "endFieldId": "gVBC-pSXzhT65M-HmrHpa",
      "cardinality": "one_to_many",
      "updateConstraint": "No action",
      "deleteConstraint": "No action",
      "name": "FK_Usuario_MovimentacaoMaterial",
      "id": 22
    },
    {
      "startTableId": "zc7H9Y8soiQeTcc4fTm89",
      "startFieldId": "cZNDs_qQtgxtLRbQUKOTD",
      "endTableId": "EgUBOf4V3YIqSYCglNDwm",
      "endFieldId": "SkTcU36OY30dsgm3OID2W",
      "cardinality": "one_to_many",
      "updateConstraint": "No action",
      "deleteConstraint": "No action",
      "name": "FK_PerfilAcesso_Usuario",
      "id": 23
    },
    {
      "startTableId": "40yak4QOnCAlDlG0q_Ny0",
      "startFieldId": "jPfcYfL6rHLpbCXb-LFxw",
      "endTableId": "EgUBOf4V3YIqSYCglNDwm",
      "endFieldId": "ypdfz29D59TuZIi7HkyUZ",
      "cardinality": "one_to_many",
      "updateConstraint": "No action",
      "deleteConstraint": "No action",
      "name": "FK_StatusUsuario_Usuario",
      "id": "xjoM_zVUYRiUGU6ZFFita"
    },
    {
      "startTableId": "l-UUUMGmE5jh0crDWddKS",
      "startFieldId": "HdHStf7sU7DSR2zhTqmKV",
      "endTableId": "6FsKnstHqrRoB-0MZ9WsS",
      "endFieldId": "u5dVmJ0xyaWsbsVuEa-BS",
      "cardinality": "one_to_many",
      "updateConstraint": "No action",
      "deleteConstraint": "No action",
      "name": "FK_Filial_Sala",
      "id": "8QvneSP1LQTSWp0U5XBgF"
    }
  ],
  "notes": [],
  "subjectAreas": [
    {
      "id": 0,
      "name": "Mod. Autenticacao e Acesso",
      "x": -1234.905203511983,
      "y": -1223.2998311075453,
      "width": 2288.3075407456026,
      "height": 572.3682141209536,
      "color": "#38eff2",
      "locked": true
    },
    {
      "id": 1,
      "name": "Mod. Gestao de Ativos",
      "x": -3241.097540478302,
      "y": -652.8517782217849,
      "width": 2514.9787847449766,
      "height": 2167.514057784108,
      "color": "#1aed9c",
      "locked": false
    },
    {
      "id": 2,
      "name": "Mod. Materiais de Limpeza",
      "x": -728.0734292854584,
      "y": -652.961161828979,
      "width": 1781.143625270068,
      "height": 2167.623441391302,
      "color": "#1b91f2",
      "locked": false
    }
  ],
  "database": "transactsql",
  "title": "Controle de Estoque com Gesto de Ativos de TI"
}